[
{
    "ref": "Michael (2016-07-30T10:52:45)",
    "name": "Cyg A",
    "components": [
        {
            "name": "1",
            "ra":"19h59m29.990s",
            "dec": "+40d43m57.53s",
            "I":43170.55527073293,
            "freq": 1.0e6,
            "index": [0.085, -0.178],
            "major-fwhm": 127.86780196141683,
            "minor-fwhm": 22.459884076169928,
            "position-angle": -74.50271323639498
        },
        {
            "name": "2",
            "ra":"19h59m24.316s",
            "dec": "+40d44m50.70s",
            "I":6374.4647292670625,
            "freq": 1.0e6,
            "index": [0.085, -0.178],
            "major-fwhm": 183.42701763410113,
            "minor-fwhm": 141.44188315233822,
            "position-angle": 43.449049376516
        }
    ]
},
{
    "ref": "Michael (2017-01-29T09:14:46)",
    "name": "Cas A",
    "components": [
        {
            "name": "1",
            "ra": "23h23m12.780s",
            "dec": "+58d50m41.00s",
            "I": 137342.67294364632,
            "freq": 1.0e6,
            "major-fwhm": 208.89999999999998,
            "minor-fwhm": 84.1,
            "index": [-0.77],
            "position-angle": 38.9
        },
        {
            "name": "2",
            "ra": "23h23m28.090s",
            "dec": "+58d49m18.10s",
            "I": 128155.37422720368,
            "freq": 1.0e6,
            "index": [-0.77],
            "major-fwhm": 230.89999999999998,
            "minor-fwhm": 121.9,
            "position-angle": 43.8
        },
        {
            "name": "3",
            "ra": "23h23m20.880s",
            "dec": "+58d50m49.92s",
            "I": 106409.98038728269,
            "freq": 1.0e6,
            "index": [-0.77],
            "major-fwhm": 173.26,
            "minor-fwhm": 63.4649,
            "position-angle": 121.902
        }
    ]
}
]
